debian/changelog
debian/compat
debian/control
debian/copyright
debian/debhelper-build-stamp
debian/files
debian/py3dist-overrides
debian/rules
images/linear_layout.png
images/linear_layout_2x4.png
images/mesh_layout.png
images/mesh_layout_2x4.png
images/torus_layout.png
images/torus_layout_2x4.png
tt_topology/__init__.py
tt_topology/__main__.py
tt_topology/backend.py
tt_topology/constants.py
tt_topology/log.py
tt_topology/tt_topology.py
tt_topology/data/wormhole/fw_defines.yaml
tt_topology/tests/test_detect_current_configs.py
tt_topology/tests/test_galaxy.py
tt_topology/tests/test_linear.py
tt_topology/tests/test_mesh.py
tt_topology/tests/test_new_mesh.py
tt_topology/tests/test_torus.py
tt_topology-1.2.18.dist-info/licenses/LICENSE
tt_topology-1.2.18.dist-info/licenses/LICENSE_understanding.txt
tt_topology-1.2.18.dist-info/METADATA
tt_topology-1.2.18.dist-info/WHEEL
tt_topology-1.2.18.dist-info/entry_points.txt
tt_topology-1.2.18.dist-info/top_level.txt
tt_topology-1.2.18.dist-info/RECORD
