Metadata-Version: 2.4
Name: tt-topology
Version: 1.2.18
Summary: ethernet topology configuration tool for Tenstorrent silicon
Author-email: Sam Bansal <sbansal@tenstorrent.com>
Maintainer-email: Sam Bansal <sbansal@tenstorrent.com>
License: 
Project-URL: Homepage, http://tenstorrent.com
Project-URL: Bug Reports, https://github.com/tenstorrent/tt-topology/issues
Project-URL: Source, https://github.com/tenstorrent/tt-topology
Classifier: Development Status :: 4 - Beta
Classifier: Environment :: Console :: Curses
Classifier: License :: OSI Approved :: Apache Software License
Classifier: Programming Language :: Python :: 3
Classifier: Programming Language :: Python :: 3.10
Classifier: Programming Language :: Python :: 3.11
Classifier: Programming Language :: Python :: 3 :: Only
Requires-Python: >=3.10
License-File: LICENSE
License-File: LICENSE_understanding.txt
Requires-Dist: tt_tools_common~=1.6.0
Requires-Dist: pyluwen~=0.8.0
Requires-Dist: elasticsearch>=8.11.0
Requires-Dist: pydantic>=1.2
Requires-Dist: networkx>=3.1
Requires-Dist: matplotlib>=3.7.4
Provides-Extra: dev
Requires-Dist: black>=24.3.0; extra == "dev"
Requires-Dist: pre-commit>=3.5.0; extra == "dev"
Dynamic: license-file
Dynamic: requires-python
